nebulous/__about__.py
nebulous/__init__.py
nebulous/game/__init__.py
nebulous/game/constants.py
nebulous/game/enums.py
nebulous/game/exceptions.py
nebulous/game/natives.py
nebulous/game/packets.py
nebulous/game/account/__init__.py
nebulous/game/models/__init__.py
nebulous/game/models/apiobjects.py
nebulous/game/models/client.py
nebulous/game/models/gameobjects.py
nebulous/game/models/netobjects.py
nebulous_py-1.5.1.dist-info/METADATA
nebulous_py-1.5.1.dist-info/WHEEL
nebulous_py-1.5.1.dist-info/RECORD
