Metadata-Version: 2.3
Name: nebulous.py
Version: 1.5.1
Summary: A Python library for utilizing the Nebulous.io UDP protocol.
Project-URL: Documentation, https://github.com/yntha/nebulous.py#readme
Project-URL: Issues, https://github.com/yntha/nebulous.py/issues
Project-URL: Source, https://github.com/yntha/nebulous.py
Author-email: yntha <126660548+yntha@users.noreply.github.com>
License-Expression: MIT
Classifier: Development Status :: 4 - Beta
Classifier: Programming Language :: Python
Classifier: Programming Language :: Python :: 3.11
Classifier: Programming Language :: Python :: 3.12
Classifier: Programming Language :: Python :: Implementation :: CPython
Classifier: Programming Language :: Python :: Implementation :: PyPy
Requires-Python: >=3.11
Requires-Dist: multiprocess>=0.70.16
Requires-Dist: pydatastreams>=1.2.6
Requires-Dist: python-dotenv>=1.0.1
Requires-Dist: requests>=2.32.3
